.DS_Store
htmldiffer/__init__.py
htmldiffer/__main__.py
htmldiffer/diff.py
htmldiffer/settings.py
htmldiffer/utils.py
htmldiffer-0.25.2.dist-info/DESCRIPTION.rst
htmldiffer-0.25.2.dist-info/METADATA
htmldiffer-0.25.2.dist-info/RECORD
htmldiffer-0.25.2.dist-info/WHEEL
htmldiffer-0.25.2.dist-info/metadata.json
htmldiffer-0.25.2.dist-info/top_level.txt
tests/.DS_Store
tests/__init__.py
tests/fixtures.py
tests/test_diff.py
tests/test_utils.py
