Metadata-Version: 2.0
Name: htmldiffer
Version: 0.25.2
Summary: HTML diff
Home-page: https://github.com/anastasia/htmldiffer
Author: Anastasia Aizman
Author-email: anastasia.aizman@gmail.com
License: MIT
Keywords: html diff
Platform: UNKNOWN
Classifier: Development Status :: 3 - Alpha
Classifier: Topic :: Utilities
Classifier: License :: OSI Approved :: MIT License
Requires-Python: >=2.7
